LICENSE.txt
MANIFEST.in
README.rst
requirements.txt
script.txt
setup.py
django_kindling.egg-info/PKG-INFO
django_kindling.egg-info/SOURCES.txt
django_kindling.egg-info/dependency_links.txt
django_kindling.egg-info/entry_points.txt
django_kindling.egg-info/requires.txt
django_kindling.egg-info/top_level.txt
kindling/__init__.py
kindling/kindling.py
kindling/templates/.gitignore
kindling/templates/config.rb
kindling/templates/fabfile.py
kindling/templates/requirements.txt
kindling/templates/settings/__init__.py
kindling/templates/settings/base.py
kindling/templates/settings/celery_development.py
kindling/templates/settings/celery_local.py
kindling/templates/settings/celery_production.py
kindling/templates/settings/development.py
kindling/templates/settings/local.py
kindling/templates/settings/production.py
kindling/templates/settings/test.py
kindling/templates/static/javascripts/default.build.js
kindling/templates/static/javascripts/jquery.cookie.js
kindling/templates/static/javascripts/jquery.js
kindling/templates/static/javascripts/main.build.js
kindling/templates/static/javascripts/main.js
kindling/templates/static/javascripts/require.js