Metadata-Version: 1.0
Name: django-kindling
Version: 0.1.4
Summary: Create nice new Django projects.
Home-page: https://github.com/radiosilence/django-kindling
Author: James Cleveland
Author-email: jc@blackflags.co.uk
License: MIT
Platform: UNKNOWN
